[
  {
    "type": 0,
    "time": {
      "from": "June 2023",
      "to": "Now"
    },
    "position": "Web Developer Intern",

    "place": "Level Up Hubs",
    "desc": [
      "Build Product landing page leveluphubs.com and growthlabs.leveluphubs.com with NextJs 13, Tailwind, Daisy UI.",
      "Build secure CURD (Create, Update, Read and Delete) operations Express and MongoDB",
      "Used ExpressJs and Google Sheets API to handle back-end for user registration for website",
      "Build secure authentication using NextAuth."
    ]
  },
  {
    "type": 0,
    "time": {
      "from": "April 2023",
      "to": "June 2023"
    },
    "position": "Web Developer Intern",

    "place": "FLAC Services",
    "desc": [
      "Build Product landing page flacservices.in with NextJs 13, Tailwind, Daisy UI.",
      "Build secure CURD (Create, Update, Read and Delete) operations Express and MongoDB",
      "Used ExpressJs and Google Sheets API to handle back-end for user registration for website",
      "Build secure authentication using NextAuth."
    ]
  },
  {
    "type": 0,
    "time": {
      "from": "Feb 2023",
      "to": "April 2023"
    },
    "position": "Web Developer Intern",
    "place": "Karma Creations",
    "desc": [
      "Build Product landing page layering.app with modern tech NextJs, Firebase, Socket.io etc",
      "Build secure authentication using NextAuth."
    ]
  },
  {
    "type": 0,
    "time": {
      "from": "April 2021",
      "to": "July 2022"
    },
    "position": "Web Developer Intern",

    "place": "Augnaar Technologies",
    "desc": [
      "Build Product landing page mentar.co.in and augnaar.com with vanilla technologies HTML, Bootstrap and JavaScript",
      "Build secure CURD (Create, Update, Read and Delete) operations using PHP and MySQL.",
      "Used PHP and MySQL to handle back-end for user registration for the App (mentar)"
    ]
  },
  {
    "type": 0,
    "time": {
      "from": "March 2022",
      "to": "Now"
    },
    "position": "Freelancer",
    "place": "",
    "desc": [
      "In demand freelancer who developes efficient and secure apps for the clients.",
      "Build projects based on reactJs, NextJs, Tailwind, Bootstrap, PHP, MySQL and MongoDB."
    ]
  },

  {
    "type": 1,
    "item": "Web Lead at Google Developer Student Clubs and GFG Student Chapter RTU - Organized over 10 events."
  },
  {
    "type": 1,
    "item": "Developing website for THAR techno-management fest RTU (rtuthar.in) which is one of the biggest in India."
  },
  {
    "type": 1,
    "item": "Developed TEDxRTU (tedxrtu.com) website."
  },
  {
    "type": 1,
    "item": "SSOC'22 contributor"
  },
  {
    "type": 1,
    "item": "Open-Source contributor in more than 30 repositories."
  }
]
